openlock/__init__.py
openlock/openlock.py
openlock-1.2.1.dist-info/AUTHORS
openlock-1.2.1.dist-info/LICENSE
openlock-1.2.1.dist-info/METADATA
openlock-1.2.1.dist-info/WHEEL
openlock-1.2.1.dist-info/top_level.txt
openlock-1.2.1.dist-info/RECORD
