Metadata-Version: 2.1
Name: openlock
Version: 1.2.1
Summary: A Python locking library not depending on inter-process locking primitives in the OS
Author-email: "Pasquale Pigazzini, Michel Van den Bergh, Joost VandeVondele" <michel.vandenbergh@uhasselt.be>
Project-URL: Homepage, https://github.com/vdbergh/openlock
Project-URL: Bug Tracker, https://github.com/vdbergh/openlock/issues
Classifier: Programming Language :: Python :: 3
Classifier: License :: OSI Approved :: MIT License
Classifier: Operating System :: OS Independent
Requires-Python: >=3.6
License-File: LICENSE
License-File: AUTHORS
